LICENSE
MANIFEST.in
README.md
setup.py
tap_adroll/__init__.py
tap_adroll/client.py
tap_adroll/discover.py
tap_adroll/streams.py
tap_adroll/sync.py
tap_adroll.egg-info/PKG-INFO
tap_adroll.egg-info/SOURCES.txt
tap_adroll.egg-info/dependency_links.txt
tap_adroll.egg-info/entry_points.txt
tap_adroll.egg-info/requires.txt
tap_adroll.egg-info/top_level.txt
tap_adroll/schemas/ad_groups.json
tap_adroll/schemas/ad_reports.json
tap_adroll/schemas/ads.json
tap_adroll/schemas/advertisables.json
tap_adroll/schemas/campaigns.json
tap_adroll/schemas/segments.json