Metadata-Version: 2.1
Name: tap-adroll
Version: 1.0.0
Summary: Singer.io tap for extracting data from Adroll
Home-page: https://singer.io
Author: Stitch
License: UNKNOWN
Platform: UNKNOWN
Classifier: Programming Language :: Python :: 3 :: Only
Provides-Extra: dev
Provides-Extra: test
